mandate/__init__.py
mandate/aws_srp.py
mandate/client.py
mandate/exceptions.py
mandate/groupobj/__init__.py
mandate/userobj/__init__.py
mandate/utils/__init__.py
mandate-2.0.0.dist-info/LICENSE
mandate-2.0.0.dist-info/WHEEL
mandate-2.0.0.dist-info/METADATA
mandate-2.0.0.dist-info/RECORD
